a2y_wxcv.cp312-win_amd64.pyd
a2y_wxcv-1.1.1.dist-info/licenses/LICENSE
a2y_wxcv-1.1.1.dist-info/METADATA
a2y_wxcv-1.1.1.dist-info/WHEEL
a2y_wxcv-1.1.1.dist-info/top_level.txt
a2y_wxcv-1.1.1.dist-info/RECORD
