Metadata-Version: 2.4
Name: a2y_wxcv
Version: 1.1.1
Summary: A module that supplies some wx widgets.
Home-page: http://www.kersci.com/a2y/wxcv.html
Author: Yu Han
Author-email: hanjunyu@163.com
License: Private
Platform: Windows
Platform: Linux
Classifier: Development Status :: 4 - Beta
Classifier: Intended Audience :: Developers
Classifier: License :: Free For Educational Use
Classifier: Programming Language :: Python :: 3.6
Classifier: Operating System :: Microsoft :: Windows :: Windows 10
Classifier: Operating System :: POSIX :: Linux
License-File: LICENSE
Requires-Dist: a2y-i18n>=1.0.0
Requires-Dist: a2y-wxctrls>=0.9.3
Requires-Dist: opencv-python>=4.0.0.0
Dynamic: author
Dynamic: author-email
Dynamic: classifier
Dynamic: description
Dynamic: description-content-type
Dynamic: home-page
Dynamic: license
Dynamic: license-file
Dynamic: platform
Dynamic: requires-dist
Dynamic: summary
